Lab2/mux.v
// output is A (when control == 0) or B (when control == 1)
module mux2(out, A, B, control);
    output out;
    input  A, B;
    input  control;
    wire   wA, wB, not_control;

    not n1(not_control, control);
    and a1(wA, A, not_control);
    and a2(wB, B, control);
    or  o1(out, wA, wB);
endmodule // mux2

// output is A (when control == 00) or B (when control == 01) or
//           C (when control == 10) or D (when control == 11)
module mux4(out, A, B, C, D, control);
    output      out;
    input       A, B, C, D;
    input [1:0] control;
    wire mux1out, mux2out;

    mux2 mux2_1(mux1out, A, B, control[0]);
    mux2 mux2_2(mux2out, C, D, control[0]);
    mux2 mux2_3(out, mux1out, mux2out, control[1]);

endmodule // mux4

Lab2/logicunit.v
// 00 -> AND, 01 -> OR, 10 -> NOR, 11 -> XOR
module logicunit(out, A, B, control);
    output      out;
    input       A, B;
    input [1:0] control;
    wire wa, wo, wn, wx;

    and a1(wa, A, B);
    or o1(wo, A, B);
    nor n1(wn, A, B);
    xor x1(wx, A, B);

    mux4 m(out, wa, wo, wn, wx, control);
endmodule // logicunit

Lab2/alu1.v
module full_adder(sum, cout, a, b, cin);
    output sum, cout;
    input  a, b, cin;
    wire   partial_s, partial_c1, partial_c2;

    xor x0(partial_s, a, b);
    xor x1(sum, partial_s, cin);
    and a0(partial_c1, a, b);
    and a1(partial_c2, partial_s, cin);
    or  o1(cout, partial_c1, partial_c2);
endmodule // full_adder

`define ALU_ADD    3'h2
`define ALU_SUB    3'h3
`define ALU_AND    3'h4
`define ALU_OR     3'h5
`define ALU_NOR    3'h6
`define ALU_XOR    3'h7

// 01x -> arithmetic, 1xx -> logic
module alu1(out, carryout, A, B, carryin, control);
    output      out, carryout;
    input       A, B, carryin;
    input [2:0] control;
    wire w1, w2, w3;

    // add code here!!!
    xor x1(w1, B, control[0]);
    full_adder f1(w2, carryout, A, w1, carryin);
    logicunit l1(w3, A, B, control[1:0]);
    mux2 m1(out, w2, w3, control[2]);

endmodule // alu1

Lab2/alu1_tb.v
module alu1_test;
    // exhaustively test your 1-bit ALU implementation by adapting mux4_tb.v
    reg A = 0;
    always #1 A = !A;
    reg B = 0;
    always #2 B = !B;
    reg C = 0;
    always #4 C = !C;

    reg [2:0] control = 0;

    initial begin
        $dumpfile("alu1.vcd");
        $dumpvars(0, alu1_test);

        // control is initially 0
        # 16 control = 3'b001; 
        # 16 control = 3'b010; 
        # 16 control = 3'b011; 
        # 16 control = 3'b100; 
        # 16 control = 3'b101; 
        # 16 control = 3'b110; 
        # 16 control = 3'b111; 
        # 16 $finish; 
    end

    wire c_out, out;
    alu1 al(out, c_out, A, B, C, control);
endmodule

Lab2/alu1.vcd
$date
	Sun Sep  6 19:55:30 2020
$end
$version
	Icarus Verilog
$end
$timescale
	1s
$end
$scope module alu1_test $end
$var wire 1 ! out $end
$var wire 1 " c_out $end
$var reg 1 # A $end
$var reg 1 $ B $end
$var reg 1 % C $end
$var reg 3 & control [2:0] $end
$scope module al $end
$var wire 1 # A $end
$var wire 1 $ B $end
$var wire 1 % carryin $end
$var wire 3 ' control [2:0] $end
$var wire 1 ( w1 $end
$var wire 1 ) w3 $end
$var wire 1 * w2 $end
$var wire 1 ! out $end
$var wire 1 " carryout $end
$scope module f1 $end
$var wire 1 # a $end
$var wire 1 ( b $end
$var wire 1 % cin $end
$var wire 1 " cout $end
$var wire 1 + partial_c1 $end
$var wire 1 , partial_c2 $end
$var wire 1 - partial_s $end
$var wire 1 * sum $end
$upscope $end
$scope module l1 $end
$var wire 1 # A $end
$var wire 1 $ B $end
$var wire 2 . control [1:0] $end
$var wire 1 / wa $end
$var wire 1 0 wn $end
$var wire 1 1 wo $end
$var wire 1 2 wx $end
$var wire 1 ) out $end
$scope module m $end
$var wire 1 / A $end
$var wire 1 1 B $end
$var wire 1 0 C $end
$var wire 1 2 D $end
$var wire 2 3 control [1:0] $end
$var wire 1 ) out $end
$var wire 1 4 mux2out $end
$var wire 1 5 mux1out $end
$scope module mux2_1 $end
$var wire 1 / A $end
$var wire 1 1 B $end
$var wire 1 6 control $end
$var wire 1 7 not_control $end
$var wire 1 5 out $end
$var wire 1 8 wA $end
$var wire 1 9 wB $end
$upscope $end
$scope module mux2_2 $end
$var wire 1 0 A $end
$var wire 1 2 B $end
$var wire 1 : control $end
$var wire 1 ; not_control $end
$var wire 1 4 out $end
$var wire 1 < wA $end
$var wire 1 = wB $end
$upscope $end
$scope module mux2_3 $end
$var wire 1 5 A $end
$var wire 1 4 B $end
$var wire 1 > control $end
$var wire 1 ? not_control $end
$var wire 1 ) out $end
$var wire 1 @ wA $end
$var wire 1 A wB $end
$upscope $end
$upscope $end
$upscope $end
$scope module m1 $end
$var wire 1 * A $end
$var wire 1 ) B $end
$var wire 1 B control $end
$var wire 1 C not_control $end
$var wire 1 ! out $end
$var wire 1 D wA $end
$var wire 1 E wB $end
$upscope $end
$upscope $end
$upscope $end
$enddefinitions $end
#0
$dumpvars
0E
0D
1C
0B
0A
0@
1?
0>
0=
1<
1;
0:
09
08
17
06
05
14
b0 3
02
01
10
0/
b0 .
0-
0,
0+
0*
0)
0(
b0 '
b0 &
0%
0$
0#
0"
0!
$end
#1
1!
1D
04
1*
0<
1-
11
00
12
1#
#2
1(
0#
1$
#3
1)
0!
1@
0D
15
0*
1"
18
0-
1+
1/
02
1#
#4
0)
0@
05
14
1!
0"
08
1<
1D
0+
0(
0/
01
10
1*
0#
0$
1%
#5
0!
0D
1"
04
0*
1,
0<
1-
11
00
12
1#
#6
1(
0#
1$
#7
1)
1!
1@
1D
15
1*
0,
18
0-
1+
1/
02
1#
#8
0)
0@
05
14
0!
0"
08
1<
0D
0+
0(
0/
01
10
0*
0#
0$
0%
#9
1!
1D
04
1*
0<
1-
11
00
12
1#
#10
1(
0#
1$
#11
1)
0!
1@
0D
15
0*
1"
18
0-
1+
1/
02
1#
#12
0)
0@
05
14
1!
0"
08
1<
1D
0+
0(
0/
01
10
1*
0#
0$
1%
#13
0!
0D
1"
04
0*
1,
0<
1-
11
00
12
1#
#14
1(
0#
1$
#15
1)
1!
1@
1D
15
1*
0,
18
0-
1+
1/
02
1#
#16
0)
0@
05
04
1!
07
0;
0"
08
0<
1D
16
1:
1-
0+
0/
01
10
1*
b1 .
b1 3
0#
0$
0%
b1 &
b1 '
#17
1)
0!
1@
0D
15
14
0*
1"
19
1=
0-
1+
11
00
12
1#
#18
0"
0+
0(
0#
1$
#19
1!
1D
04
1*
0=
1-
1/
02
1#
#20
0)
0@
05
0!
09
0D
1"
1(
0/
01
10
0*
1,
0#
0$
1%
#21
1)
1!
1@
1D
15
14
1*
0,
19
1=
0-
1+
11
00
12
1#
#22
0"
0+
0(
0#
1$
#23
0!
0D
1"
04
0*
1,
0=
1-
1/
02
1#
#24
0)
0@
05
1!
09
1D
0"
1(
0/
01
10
1*
0,
0#
0$
0%
#25
1)
0!
1@
0D
15
14
0*
1"
19
1=
0-
1+
11
00
12
1#
#26
0"
0+
0(
0#
1$
#27
1!
1D
04
1*
0=
1-
1/
02
1#
#28
0)
0@
05
0!
09
0D
1"
1(
0/
01
10
0*
1,
0#
0$
1%
#29
1)
1!
1@
1D
15
14
1*
0,
19
1=
0-
1+
11
00
12
1#
#30
0"
0+
0(
0#
1$
#31
0!
0D
1"
04
0*
1,
0=
1-
1/
02
1#
#32
1A
14
1)
1<
0@
05
0!
17
1;
0?
09
0D
0"
06
0:
1>
0-
0/
01
10
0*
0,
b10 .
b10 3
0#
0$
0%
b10 &
b10 '
#33
0)
1!
0A
1D
04
1*
0<
1-
11
00
12
1#
#34
1(
0#
1$
#35
0!
0D
15
0*
1"
18
0-
1+
1/
02
1#
#36
1)
1A
05
14
1!
0"
08
1<
1D
0+
0(
0/
01
10
1*
0#
0$
1%
#37
0)
0!
0A
0D
1"
04
0*
1,
0<
1-
11
00
12
1#
#38
1(
0#
1$
#39
1!
1D
15
1*
0,
18
0-
1+
1/
02
1#
#40
1)
1A
05
14
0!
0"
08
1<
0D
0+
0(
0/
01
10
0*
0#
0$
0%
#41
0)
1!
0A
1D
04
1*
0<
1-
11
00
12
1#
#42
1(
0#
1$
#43
0!
0D
15
0*
1"
18
0-
1+
1/
02
1#
#44
1)
1A
05
14
1!
0"
08
1<
1D
0+
0(
0/
01
10
1*
0#
0$
1%
#45
0)
0!
0A
0D
1"
04
0*
1,
0<
1-
11
00
12
1#
#46
1(
0#
1$
#47
1!
1D
15
1*
0,
18
0-
1+
1/
02
1#
#48
0)
0A
05
04
1!
07
0;
0"
08
0<
1D
16
1:
1-
0+
0/
01
10
1*
b11 .
b11 3
0#
0$
0%
b11 &
b11 '
#49
1)
0!
1A
0D
15
14
0*
1"
19
1=
0-
1+
11
00
12
1#
#50
0"
0+
0(
0#
1$
#51
0)
1!
0A
1D
04
1*
0=
1-
1/
02
1#
#52
05
0!
09
0D
1"
1(
0/
01
10
0*
1,
0#
0$
1%
#53
1)
1!
1A
1D
15
14
1*
0,
19
1=
0-
1+
11
00
12
1#
#54
0"
0+
0(
0#
1$
#55
0)
0!
0A
0D
1"
04
0*
1,
0=
1-
1/
02
1#
#56
05
1!
09
1D
0"
1(
0/
01
10
1*
0,
0#
0$
0%
#57
1)
0!
1A
0D
15
14
0*
1"
19
1=
0-
1+
11
00
12
1#
#58
0"
0+
0(
0#
1$
#59
0)
1!
0A
1D
04
1*
0=
1-
1/
02
1#
#60
05
0!
09
0D
1"
1(
0/
01
10
0*
1,
0#
0$
1%
#61
1)
1!
1A
1D
15
14
1*
0,
19
1=
0-
1+
11
00
12
1#
#62
0"
0+
0(
0#
1$
#63
0)
0!
0A
0D
1"
04
0*
1,
0=
1-
1/
02
1#
#64
14
1<
05
17
1;
1?
09
0"
06
0:
0>
0C
0-
0/
01
10
0*
0,
b0 .
b0 3
1B
0#
0$
0%
b100 &
b100 '
#65
04
1*
0<
1-
11
00
12
1#
#66
1(
0#
1$
#67
1!
1E
1)
1@
15
0*
1"
18
0-
1+
1/
02
1#
#68
0!
0E
0)
0@
05
14
0"
08
1<
0+
0(
0/
01
10
1*
0#
0$
1%
#69
1"
04
0*
1,
0<
1-
11
00
12
1#
#70
1(
0#
1$
#71
1!
1E
1)
1@
15
1*
0,
18
0-
1+
1/
02
1#
#72
0!
0E
0)
0@
05
14
0"
08
1<
0+
0(
0/
01
10
0*
0#
0$
0%
#73
04
1*
0<
1-
11
00
12
1#
#74
1(
0#
1$
#75
1!
1E
1)
1@
15
0*
1"
18
0-
1+
1/
02
1#
#76
0!
0E
0)
0@
05
14
0"
08
1<
0+
0(
0/
01
10
1*
0#
0$
1%
#77
1"
04
0*
1,
0<
1-
11
00
12
1#
#78
1(
0#
1$
#79
1!
1E
1)
1@
15
1*
0,
18
0-
1+
1/
02
1#
#80
0!
0E
0)
0@
05
04
07
0;
0"
08
0<
16
1:
1-
0+
0/
01
10
1*
b1 .
b1 3
0#
0$
0%
b101 &
b101 '
#81
1!
1E
1)
1@
15
14
0*
1"
19
1=
0-
1+
11
00
12
1#
#82
0"
0+
0(
0#
1$
#83
04
1*
0=
1-
1/
02
1#
#84
0!
0E
0)
0@
05
09
1"
1(
0/
01
10
0*
1,
0#
0$
1%
#85
1!
1E
1)
1@
15
14
1*
0,
19
1=
0-
1+
11
00
12
1#
#86
0"
0+
0(
0#
1$
#87
1"
04
0*
1,
0=
1-
1/
02
1#
#88
0!
0E
0)
0@
05
09
0"
1(
0/
01
10
1*
0,
0#
0$
0%
#89
1!
1E
1)
1@
15
14
0*
1"
19
1=
0-
1+
11
00
12
1#
#90
0"
0+
0(
0#
1$
#91
04
1*
0=
1-
1/
02
1#
#92
0!
0E
0)
0@
05
09
1"
1(
0/
01
10
0*
1,
0#
0$
1%
#93
1!
1E
1)
1@
15
14
1*
0,
19
1=
0-
1+
11
00
12
1#
#94
0"
0+
0(
0#
1$
#95
1"
04
0*
1,
0=
1-
1/
02
1#
#96
1!
1A
1E
14
1)
1<
0@
05
17
1;
0?
09
0"
06
0:
1>
0-
0/
01
10
0*
0,
b10 .
b10 3
0#
0$
0%
b110 &
b110 '
#97
0!
0E
0)
0A
04
1*
0<
1-
11
00
12
1#
#98
1(
0#
1$
#99
15
0*
1"
18
0-
1+
1/
02
1#
#100
1!
1E
1)
1A
05
14
0"
08
1<
0+
0(
0/
01
10
1*
0#
0$
1%
#101
0!
0E
0)
0A
1"
04
0*
1,
0<
1-
11
00
12
1#
#102
1(
0#
1$
#103
15
1*
0,
18
0-
1+
1/
02
1#
#104
1!
1E
1)
1A
05
14
0"
08
1<
0+
0(
0/
01
10
0*
0#
0$
0%
#105
0!
0E
0)
0A
04
1*
0<
1-
11
00
12
1#
#106
1(
0#
1$
#107
15
0*
1"
18
0-
1+
1/
02
1#
#108
1!
1E
1)
1A
05
14
0"
08
1<
0+
0(
0/
01
10
1*
0#
0$
1%
#109
0!
0E
0)
0A
1"
04
0*
1,
0<
1-
11
00
12
1#
#110
1(
0#
1$
#111
15
1*
0,
18
0-
1+
1/
02
1#
#112
0!
0E
0)
0A
05
04
07
0;
0"
08
0<
16
1:
1-
0+
0/
01
10
1*
b11 .
b11 3
0#
0$
0%
b111 &
b111 '
#113
1!
1E
1)
1A
15
14
0*
1"
19
1=
0-
1+
11
00
12
1#
#114
0"
0+
0(
0#
1$
#115
0!
0E
0)
0A
04
1*
0=
1-
1/
02
1#
#116
05
09
1"
1(
0/
01
10
0*
1,
0#
0$
1%
#117
1!
1E
1)
1A
15
14
1*
0,
19
1=
0-
1+
11
00
12
1#
#118
0"
0+
0(
0#
1$
#119
0!
0E
0)
0A
1"
04
0*
1,
0=
1-
1/
02
1#
#120
05
09
0"
1(
0/
01
10
1*
0,
0#
0$
0%
#121
1!
1E
1)
1A
15
14
0*
1"
19
1=
0-
1+
11
00
12
1#
#122
0"
0+
0(
0#
1$
#123
0!
0E
0)
0A
04
1*
0=
1-
1/
02
1#
#124
05
09
1"
1(
0/
01
10
0*
1,
0#
0$
1%
#125
1!
1E
1)
1A
15
14
1*
0,
19
1=
0-
1+
11
00
12
1#
#126
0"
0+
0(
0#
1$
#127
0!
0E
0)
0A
1"
04
0*
1,
0=
1-
1/
02
1#
#128
05
09
0"
1(
0/
01
10
1*
0,
0#
0$
0%
