Lab2/mux.v
// output is A (when control == 0) or B (when control == 1)
module mux2(out, A, B, control);
    output out;
    input  A, B;
    input  control;
    wire   wA, wB, not_control;

    not n1(not_control, control);
    and a1(wA, A, not_control);
    and a2(wB, B, control);
    or  o1(out, wA, wB);
endmodule // mux2

// output is A (when control == 00) or B (when control == 01) or
//           C (when control == 10) or D (when control == 11)
module mux4(out, A, B, C, D, control);
    output      out;
    input       A, B, C, D;
    input [1:0] control;
    wire mux1out, mux2out;

    mux2 mux2_1(mux1out, A, B, control[0]);
    mux2 mux2_2(mux2out, C, D, control[0]);
    mux2 mux2_3(out, mux1out, mux2out, control[1]);

endmodule // mux4

Lab2/logicunit.v
// 00 -> AND, 01 -> OR, 10 -> NOR, 11 -> XOR
module logicunit(out, A, B, control);
    output      out;
    input       A, B;
    input [1:0] control;
    wire wa, wo, wn, wx;

    and a1(wa, A, B);
    or o1(wo, A, B);
    nor n1(wn, A, B);
    xor x1(wx, A, B);

    mux4 m(out, wa, wo, wn, wx, control);
endmodule // logicunit

Lab2/logicunit_tb.v
module logicunit_test;
    // these are inputs to "logicunit under test"
    reg A = 0;
    always #2 A = !A;
    reg B = 0;
    always #1 B = !B;

    reg [1:0] control;
    
    // wires for the outputs of "logicunit under test"
    wire out;
    
    // the circuit under test
    logicunit l(out, A, B, control);  
    
    initial begin               // initial = run at beginning of simulation
                                // begin/end = associate block with initial

        $dumpfile("logicunit.vcd");
        $dumpvars(0, logicunit_test);

        // test all input combinations
        control = 0; #4
        control = 1; #4
        control = 2; #4
        control = 3; #3
        $finish; // end the simulation
    end                  
   
    initial begin
        $display("A   B   Control    Out");
        $monitor("A=%b B=%b Control=%b Out=%b", A, B, control, out);
    end

endmodule // logicunit_test

Lab2/logicunit.vcd
$date
	Sun Sep  6 19:55:30 2020
$end
$version
	Icarus Verilog
$end
$timescale
	1s
$end
$scope module logicunit_test $end
$var wire 1 ! out $end
$var reg 1 " A $end
$var reg 1 # B $end
$var reg 2 $ control [1:0] $end
$scope module l $end
$var wire 1 " A $end
$var wire 1 # B $end
$var wire 2 % control [1:0] $end
$var wire 1 & wa $end
$var wire 1 ' wn $end
$var wire 1 ( wo $end
$var wire 1 ) wx $end
$var wire 1 ! out $end
$scope module m $end
$var wire 1 & A $end
$var wire 1 ( B $end
$var wire 1 ' C $end
$var wire 1 ) D $end
$var wire 2 * control [1:0] $end
$var wire 1 ! out $end
$var wire 1 + mux2out $end
$var wire 1 , mux1out $end
$scope module mux2_1 $end
$var wire 1 & A $end
$var wire 1 ( B $end
$var wire 1 - control $end
$var wire 1 . not_control $end
$var wire 1 , out $end
$var wire 1 / wA $end
$var wire 1 0 wB $end
$upscope $end
$scope module mux2_2 $end
$var wire 1 ' A $end
$var wire 1 ) B $end
$var wire 1 1 control $end
$var wire 1 2 not_control $end
$var wire 1 + out $end
$var wire 1 3 wA $end
$var wire 1 4 wB $end
$upscope $end
$scope module mux2_3 $end
$var wire 1 , A $end
$var wire 1 + B $end
$var wire 1 5 control $end
$var wire 1 6 not_control $end
$var wire 1 ! out $end
$var wire 1 7 wA $end
$var wire 1 8 wB $end
$upscope $end
$upscope $end
$upscope $end
$upscope $end
$enddefinitions $end
#0
$dumpvars
08
07
16
05
04
13
12
01
00
0/
1.
0-
0,
1+
b0 *
0)
0(
1'
0&
b0 %
b0 $
0#
0"
0!
$end
#1
0+
03
1(
0'
1)
1#
#2
0#
1"
#3
1!
17
1,
1/
1&
0)
1#
#4
0!
07
0,
0/
0.
02
0&
0(
1'
1-
11
0#
0"
b1 $
b1 %
b1 *
#5
1!
17
1,
1+
10
14
1(
0'
1)
1#
#6
0#
1"
#7
0+
04
1&
0)
1#
#8
18
1!
1+
0,
07
13
1.
00
12
06
0&
0(
1'
0-
01
15
0#
0"
b10 $
b10 %
b10 *
#9
0!
08
0+
03
1(
0'
1)
1#
#10
0#
1"
#11
1,
1/
1&
0)
1#
#12
0,
0/
0.
02
0&
0(
1'
1-
11
0#
0"
b11 $
b11 %
b11 *
#13
1!
18
1,
1+
10
14
1(
0'
1)
1#
#14
0#
1"
#15
0!
08
0+
04
1&
0)
1#
